black_pack/__init__.py
black_pack/version.py
black_pack/apps/main.py
black_pack/resources/GPLv3.txt
black_pack/resources/MIT.txt
black_pack/resources/README.rst
black_pack/resources/github_workflows_release.yml
black_pack/resources/github_workflows_test.yml
black_pack/resources/gitignore_commit_8e67b94_2023-09-10
black_pack/resources/pyproject.toml
black_pack/resources/requirements.txt
black_pack-0.1.16.dist-info/licenses/LICENSE
black_pack-0.1.16.dist-info/METADATA
black_pack-0.1.16.dist-info/WHEEL
black_pack-0.1.16.dist-info/entry_points.txt
black_pack-0.1.16.dist-info/top_level.txt
black_pack-0.1.16.dist-info/RECORD
