Metadata-Version: 2.4
Name: black_pack
Version: 0.1.16
Summary: Linting and structural checking for python-packages
Home-page: https://github.com/cherenkov-plenoscope/black_pack
Author: Sebastian Achim Mueller
Author-email: sebastian-achim.mueller@mpi-hd.mpg.de
Classifier: Programming Language :: Python :: 3
Classifier: License :: OSI Approved :: MIT License
Classifier: Operating System :: OS Independent
Classifier: Natural Language :: English
License-File: LICENSE
Requires-Dist: black
Requires-Dist: cython-lint
Requires-Dist: toml
Requires-Dist: yamlcore
Requires-Dist: restructuredtext-lint
Requires-Dist: pyyaml
Requires-Dist: dictdiffer
Dynamic: author
Dynamic: author-email
Dynamic: classifier
Dynamic: description
Dynamic: description-content-type
Dynamic: home-page
Dynamic: license-file
Dynamic: requires-dist
Dynamic: summary
